COPYING
INSTALL
MANIFEST.in
ez_setup.py
hidx.desktop
hidx.py
setup.py
GUI/Ui_aboutHiDX.py
GUI/Ui_dbserver.py
GUI/Ui_main.py
GUI/Ui_webview.py
GUI/__init__.py
GUI/aboutHiDX.py
GUI/dbserver.py
GUI/icons_rc.py
GUI/main.py
GUI/webview.py
GUI/stats/__init__.py
GUI/stats/explore.py
GUI/viz/Ui_motionchart.py
GUI/viz/__init__.py
GUI/viz/icons_rc.py
GUI/viz/motionchart.py
GUI/viz/scatmat.py
hidx.egg-info/PKG-INFO
hidx.egg-info/SOURCES.txt
hidx.egg-info/dependency_links.txt
hidx.egg-info/entry_points.txt
hidx.egg-info/requires.txt
hidx.egg-info/top_level.txt
hidx.egg-info/zip-safe