Metadata-Version: 1.0
Name: hidx
Version: 0.5
Summary: High Dimensional Data Explorer
Home-page: http://code.google.com/p/hidx/
Author: Flavio Codeco Coelho
Author-email: fccoelho@gmail.com
License: GPL
Platform: UNKNOWN
